aioproperty
