Metadata-Version: 2.1
Name: aioproperty
Version: 0.3.2
Summary: truely async properties
Home-page: UNKNOWN
Author: Viktorov A.G.
Author-email: andvikt@gmail.com
License: MIT
Platform: UNKNOWN
Requires-Python: >=3.7
